dithering-0.1.27.dist-info/METADATA
dithering-0.1.27.dist-info/WHEEL
dithering-0.1.27.dist-info/license_files/LICENSE
dithering/__init__.py
dithering/__init__.pyi
dithering/py.typed
dithering/dithering.pypy39-pp73-arm-linux-gnu.so
dithering-0.1.27.dist-info/RECORD
