Metadata-Version: 2.1
Name: dithering
Version: 0.1.27
Classifier: Programming Language :: Rust
Classifier: Programming Language :: Python :: Implementation :: CPython
Classifier: Programming Language :: Python :: Implementation :: PyPy
License-File: LICENSE
Summary: Efficient implementations of various image dithering methods.
Keywords: image processing,dithering,rust
Home-Page: https://backyardml.github.io/
Author: Patrik Larsson <patrik@backyardml.se>
Author-email: Patrik Larsson <patrik@backyardml.se>
Requires-Python: >=3.7
Project-URL: Source Code, https://github.com/BackyardML/dithering
